.gitignore
LICENSE.md
README.md
extract_locon.py
merge_locon.py
requirements.txt
setup.py
experiments/locon_extract_test.py
experiments/locon_merge_test.py
experiments/singular_value_test.py
locon/__init__.py
locon/kohya_model_utils.py
locon/kohya_utils.py
locon/locon.py
locon/locon_kohya.py
locon/utils.py
locon.egg-info/PKG-INFO
locon.egg-info/SOURCES.txt
locon.egg-info/dependency_links.txt
locon.egg-info/not-zip-safe
locon.egg-info/requires.txt
locon.egg-info/top_level.txt